poetry_patches/__init__.py
poetry_patches/commands.py
poetry_patches/patcher.py
poetry_patches/plugins.py
poetry_patches/state/__init__.py
poetry_patches/state/backup.py
poetry_patches/state/meta.py
poetry_patches-0.1.6.dist-info/entry_points.txt
poetry_patches-0.1.6.dist-info/LICENSE
poetry_patches-0.1.6.dist-info/METADATA
poetry_patches-0.1.6.dist-info/WHEEL
poetry_patches-0.1.6.dist-info/RECORD
